{
  "openapi": "3.0.1",
  "info": {
    "title": "StudentCourses",
    "version": "1.0"
  },
  "paths": {
    "/api/admins": {
      "post": {
        "tags": [
          "Admin"
        ],
        "requestBody": {
          "content": {
            "application/json": {
              "schema": {
                "$ref": "#/components/schemas/AdminDTO"
              }
            },
            "text/json": {
              "schema": {
                "$ref": "#/components/schemas/AdminDTO"
              }
            },
            "application/*+json": {
              "schema": {
                "$ref": "#/components/schemas/AdminDTO"
              }
            }
          }
        },
        "responses": {
          "200": {
            "description": "OK"
          }
        }
      },
      "get": {
        "tags": [
          "Admin"
        ],
        "responses": {
          "200": {
            "description": "OK"
          }
        }
      }
    },
    "/api/auth/login": {
      "post": {
        "tags": [
          "Auth"
        ],
        "requestBody": {
          "content": {
            "application/json": {
              "schema": {
                "$ref": "#/components/schemas/LoginDTO"
              }
            },
            "text/json": {
              "schema": {
                "$ref": "#/components/schemas/LoginDTO"
              }
            },
            "application/*+json": {
              "schema": {
                "$ref": "#/components/schemas/LoginDTO"
              }
            }
          }
        },
        "responses": {
          "200": {
            "description": "OK"
          }
        }
      }
    },
    "/WeatherForecast": {
      "get": {
        "tags": [
          "WeatherForecast"
        ],
        "operationId": "GetWeatherForecast",
        "responses": {
          "200": {
            "description": "OK",
            "content": {
              "text/plain": {
                "schema": {
                  "type": "array",
                  "items": {
                    "$ref": "#/components/schemas/WeatherForecast"
                  }
                }
              },
              "application/json": {
                "schema": {
                  "type": "array",
                  "items": {
                    "$ref": "#/components/schemas/WeatherForecast"
                  }
                }
              },
              "text/json": {
                "schema": {
                  "type": "array",
                  "items": {
                    "$ref": "#/components/schemas/WeatherForecast"
                  }
                }
              }
            }
          }
        }
      }
    }
  },
  "components": {
    "schemas": {
      "AdminDTO": {
        "type": "object",
        "properties": {
          "fullName": {
            "type": "string",
            "nullable": true
          },
          "email": {
            "type": "string",
            "nullable": true
          },
          "password": {
            "type": "string",
            "nullable": true
          }
        },
        "additionalProperties": false
      },
      "LoginDTO": {
        "type": "object",
        "properties": {
          "email": {
            "type": "string",
            "nullable": true
          },
          "password": {
            "type": "string",
            "nullable": true
          }
        },
        "additionalProperties": false
      },
      "WeatherForecast": {
        "type": "object",
        "properties": {
          "date": {
            "type": "string",
            "format": "date"
          },
          "temperatureC": {
            "type": "integer",
            "format": "int32"
          },
          "temperatureF": {
            "type": "integer",
            "format": "int32",
            "readOnly": true
          },
          "summary": {
            "type": "string",
            "nullable": true
          }
        },
        "additionalProperties": false
      }
    }
  }
}